calcsum/__init__.py
calcsum/calcsum.py
testpackage156-0.0.1.dist-info/METADATA
testpackage156-0.0.1.dist-info/WHEEL
testpackage156-0.0.1.dist-info/top_level.txt
testpackage156-0.0.1.dist-info/RECORD
