Metadata-Version: 2.1
Name: testpackage156
Version: 0.0.1
Summary: short package description
Home-page: https://gitlab.com/codasteroid/basicpkg
Author: author
Author-email: author@example.com
Project-URL: Bug Tracker, https://gitlab.com/codasteroid/basicpkg/-/issues
Classifier: Programming Language :: Python :: 3
Classifier: License :: OSI Approved :: MIT License
Classifier: Operating System :: OS Independent
Requires-Python: >=3.6
